pyramid_wtforms/__about__.py
pyramid_wtforms/__init__.py
pyramid_wtforms/fields.py
pyramid_wtforms/forms.py
pyramid_wtforms/storage.py
pyramid_wtforms/validators.py
pyramid_wtforms/widgets.py
pyramid_wtforms-3.1.0.dist-info/METADATA
pyramid_wtforms-3.1.0.dist-info/WHEEL
pyramid_wtforms-3.1.0.dist-info/licenses/LICENSE
pyramid_wtforms-3.1.0.dist-info/RECORD
